conditional_gate/main.v
/*
Combinational logic-centered --> must use blocking assignment and always block with sensitivity list of all inputs.
*/

module conditional_gate (
    output reg F,
    input wire A, B, C, D
);

    always @ (A, B, C, D)
        begin
            if      (A == 1'b0 && B == 1'b0 && C == 1'b0 && D == 1'b1)
                F = 1'b1;
            else if (A == 1'b0 && B == 1'b0 && C == 1'b1 && D == 1'b1)
                F = 1'b1;
            else if (A == 1'b1 && B == 1'b0 && C == 1'b0 && D == 1'b1)
                F = 1'b1;
            else if (A == 1'b1 && B == 1'b0 && C == 1'b1 && D == 1'b1)
                F = 1'b1;
            else
                F = 1'b0;
        end

endmodule

module tb_conditional_gate();

wire f;
reg a, b, c, d;

conditional_gate comp_1(.F(f), .A(a), .B(b), .C(c), .D(d));

initial
    begin
        $dumpfile("conditional_gate.vcd");
        $dumpvars(0, tb_conditional_gate);
        {a, b, c, d} = 4'b0000;
        #1
        {a, b, c, d} = 4'b0001;
        #1
        {a, b, c, d} = 4'b0010;
        #1
        {a, b, c, d} = 4'b0011;
        #1
        {a, b, c, d} = 4'b0100;
        #1
        {a, b, c, d} = 4'b0101;
        #1
        {a, b, c, d} = 4'b0110;
        #1
        {a, b, c, d} = 4'b0111;
        #1
        {a, b, c, d} = 4'b1000;
        #1
        {a, b, c, d} = 4'b1001;
        #1
        {a, b, c, d} = 4'b1010;
        #1
        {a, b, c, d} = 4'b1011;
        #1
        {a, b, c, d} = 4'b1100;
        #1
        {a, b, c, d} = 4'b1101;
        #1
        {a, b, c, d} = 4'b1110;
        #1
        {a, b, c, d} = 4'b1111;
        $finish;
    end

    always @(f)
        $monitor("time=%0t abcd = %b%b%b%b f = %b", $time, a, b, c, d, f);

endmodule

if_gate/conditional_gate.vcd
$date
	Sat Dec  5 00:47:24 2020
$end
$version
	Icarus Verilog
$end
$timescale
	1s
$end
$scope module tb_conditional_gate $end
$var wire 1 ! f $end
$var reg 1 " a $end
$var reg 1 # b $end
$var reg 1 $ c $end
$var reg 1 % d $end
$scope module comp_1 $end
$var wire 1 " A $end
$var wire 1 # B $end
$var wire 1 $ C $end
$var wire 1 % D $end
$var reg 1 ! F $end
$upscope $end
$upscope $end
$enddefinitions $end
#0
$dumpvars
0%
0$
0#
0"
0!
$end
#1
1!
1%
#2
0!
1$
0%
#3
1!
1%
#4
0!
1#
0$
0%
#5
1%
#6
1$
0%
#7
1%
#8
1"
0#
0$
0%
#9
1!
1%
#10
0!
1$
0%
#11
1!
1%
#12
0!
1#
0$
0%
#13
1%
#14
1$
0%
#15
1%
