dataflow_gate_0/main.v
// iverilog -o main.vvp main.v

module dataflow_gate_0 (
    output wire F,
    input wire A, B, C
);

    assign F = (!C && (!A || B) ) ? 1'b1 : 1'b0;

endmodule

module tb_dataflow_gate_0 ();

reg a, b, c;
wire f;

dataflow_gate_0 gate_1(.F(f), .A(a), .B(b), .C(c));

initial
    begin
        $dumpfile("dataflow_gate_0.vcd");
        $dumpvars(0, tb_dataflow_gate_0);
        a = 1'b0;
        b = 1'b0;
        c = 1'b0;
        #1
        a = 1'b0;
        b = 1'b0;
        c = 1'b1;
        #1
        a = 1'b0;
        b = 1'b1;
        c = 1'b0;
        #1
        a = 1'b0;
        b = 1'b1;
        c = 1'b1;
        #1
        a = 1'b1;
        b = 1'b0;
        c = 1'b0;
        #1
        a = 1'b1;
        b = 1'b0;
        c = 1'b1;
        #1
        a = 1'b1;
        b = 1'b1;
        c = 1'b0;
        #1
        a = 1'b1;
        b = 1'b1;
        c = 1'b1;
        #10
        $finish;
    end

endmodule

dataflow_gate_0/dataflow_gate_0.vcd
$date
	Thu Dec  3 00:21:15 2020
$end
$version
	Icarus Verilog
$end
$timescale
	1s
$end
$scope module tb_dataflow_gate_0 $end
$var wire 1 ! f $end
$var reg 1 " a $end
$var reg 1 # b $end
$var reg 1 $ c $end
$scope module gate_1 $end
$var wire 1 " A $end
$var wire 1 # B $end
$var wire 1 $ C $end
$var wire 1 ! F $end
$upscope $end
$upscope $end
$enddefinitions $end
#0
$dumpvars
0$
0#
0"
1!
$end
#1
0!
1$
#2
1!
0$
1#
#3
0!
1$
#4
0$
0#
1"
#5
1$
#6
1!
0$
1#
#7
0!
1$
