demux_1_to_8/main.v

/*
Implementation of 1-to-8 demultiplexer
Created by jefflgaol@icloud.com
*/

module demux_1to8 (
    output wire [7:0] F,
    input wire A,
    input wire [2:0] Sel
);

    assign F[0] = (Sel == 3'b000) ? A : 1'b0;
    assign F[1] = (Sel == 3'b001) ? A : 1'b0;
    assign F[2] = (Sel == 3'b010) ? A : 1'b0;
    assign F[3] = (Sel == 3'b011) ? A : 1'b0;
    assign F[4] = (Sel == 3'b100) ? A : 1'b0;
    assign F[5] = (Sel == 3'b101) ? A : 1'b0;
    assign F[6] = (Sel == 3'b110) ? A : 1'b0;
    assign F[7] = (Sel == 3'b111) ? A : 1'b0;

endmodule

module tb_demux_1to8 ();

wire [7:0] f;
reg a;
reg [2:0] sel;

demux_1to8 gate_1(f, a, sel);

initial
    begin
        $dumpfile("demux_1to8.vcd");
        $dumpvars(0, tb_demux_1to8);
        // Test A = 1'b0
        a = 1'b0;
        sel = 3'b000;
        #1
        sel = 3'b001;
        #1
        sel = 3'b010;
        #1
        sel = 3'b011;
        #1
        sel = 3'b100;
        #1
        sel = 3'b101;
        #1
        sel = 3'b110;
        #1
        sel = 3'b111;
        #1
        // Test A = 1'b1
        a = 1'b1;
        sel = 3'b000;
        #1
        sel = 3'b001;
        #1
        sel = 3'b010;
        #1
        sel = 3'b011;
        #1
        sel = 3'b100;
        #1
        sel = 3'b101;
        #1
        sel = 3'b110;
        #1
        sel = 3'b111;
        $finish;
    end

always @(f)
    $monitor("time=%0t \t a = %b sel = %b f = %b", $time, a, sel, f);

endmodule

demux_1_to_8/demux_1to8.vcd
$date
	Wed Dec  2 14:18:19 2020
$end
$version
	Icarus Verilog
$end
$timescale
	1s
$end
$scope module tb_demux_1to8 $end
$var wire 8 ! f [7:0] $end
$var reg 1 " a $end
$var reg 3 # sel [2:0] $end
$scope module gate_1 $end
$var wire 1 " A $end
$var wire 3 $ Sel [2:0] $end
$var wire 8 % F [7:0] $end
$upscope $end
$upscope $end
$enddefinitions $end
#0
$dumpvars
b0 %
b0 $
b0 #
0"
b0 !
$end
#1
b1 #
b1 $
#2
b10 #
b10 $
#3
b11 #
b11 $
#4
b100 #
b100 $
#5
b101 #
b101 $
#6
b110 #
b110 $
#7
b111 #
b111 $
#8
b1 !
b1 %
b0 #
b0 $
1"
#9
b10 !
b10 %
b1 #
b1 $
#10
b100 !
b100 %
b10 #
b10 $
#11
b1000 !
b1000 %
b11 #
b11 $
#12
b10000 !
b10000 %
b100 #
b100 $
#13
b100000 !
b100000 %
b101 #
b101 $
#14
b1000000 !
b1000000 %
b110 #
b110 $
#15
b10000000 !
b10000000 %
b111 #
b111 $
