custom_gate_3/main.v

/*
Implementation of SOP: 0,1,4 using K-Map
Created by jefflgaol@icloud.com
F = C'B'+A'B'
  = B'(A'+C')
*/

module custom_gate_3 (
    output wire F,
    input wire A, B, C
);

    assign F = ~B & (~A | ~C);

endmodule

module tb_custom_gate_3 ();

reg a, b, c;
wire f;

custom_gate_3 gate_1(.F(f), .A(a), .B(b), .C(c));

initial
    begin
        $dumpfile("custom_gate_3.vcd");
        $dumpvars(0, tb_custom_gate_3);
        a = 1'b0;
        b = 1'b0;
        c = 1'b0;
        #1
        a = 1'b0;
        b = 1'b0;
        c = 1'b1;
        #1
        a = 1'b0;
        b = 1'b1;
        c = 1'b0;
        #1
        a = 1'b0;
        b = 1'b1;
        c = 1'b1;
        #1
        a = 1'b1;
        b = 1'b0;
        c = 1'b0;
        #1
        a = 1'b1;
        b = 1'b0;
        c = 1'b1;
        #1
        a = 1'b1;
        b = 1'b1;
        c = 1'b0;
        #1
        a = 1'b1;
        b = 1'b1;
        c = 1'b1;
        $finish;
    end

always @(f)
    $monitor("time=%0t \t a = %b b = %b c = %b y = %b", $time, a, b, c, f);

endmodule

custom_gate_3/custom_gate_3.vcd
$date
	Wed Dec  2 13:05:34 2020
$end
$version
	Icarus Verilog
$end
$timescale
	1s
$end
$scope module tb_custom_gate_3 $end
$var wire 1 ! f $end
$var reg 1 " a $end
$var reg 1 # b $end
$var reg 1 $ c $end
$scope module gate_1 $end
$var wire 1 " A $end
$var wire 1 # B $end
$var wire 1 $ C $end
$var wire 1 ! F $end
$upscope $end
$upscope $end
$enddefinitions $end
#0
$dumpvars
0$
0#
0"
1!
$end
#1
1$
#2
0!
0$
1#
#3
1$
#4
1!
0$
0#
1"
#5
0!
1$
#6
0$
1#
#7
1$
