register_32_bit/main.v
module register_32_bit (
    output reg [31:0] Data_Out,
    input wire [31:0] Data_In,
    input wire Enable, Clock, Reset
);

    always @ (posedge Clock or negedge Reset)
        begin
            if (!Reset)
                begin
                    Data_Out <= 32'h0;
                end
            else
                if (Enable)
                    begin
                        Data_Out <= Data_In;
                    end
        end

endmodule

module tb_register_32_bit();

wire [31:0] data_out;
reg [31:0] data_in;
reg enable, clock, reset;

register_32_bit comp_1(.Data_Out(data_out), .Data_In(data_in), .Enable(enable), .Clock(clock), .Reset(reset));

// Enable
initial
    begin
        enable = 1'b0;
        #9
        enable = 1'b1;
    end

// Clock
initial
    begin
        clock = 1'b0;
    end

always
    begin
        #1 clock = ~clock;
    end

// Reset
initial
    begin
        reset = 1'b1;
        #2 reset = 1'b0;
        #2 reset = 1'b1;
    end

initial
    begin
        $dumpfile("register_32_bit.vcd");
        $dumpvars(0, tb_register_32_bit);
        data_in = 32'hA;
        #2 data_in = 32'hB;
        #2 data_in = 32'hC;
        #2 data_in = 32'hAC;
        #2 data_in = 32'h32;
        #2 data_in = 32'h50;
        #2 enable = 1'b0;
        #2 data_in = 32'h20;
        #2 data_in = 32'hB;
        #2 data_in = 32'hC;
        #2 data_in = 32'hAC;
        #2 data_in = 32'h32;
        #2 data_in = 32'h50;
        #2 data_in = 32'h20;
        $finish;
    end

endmodule

register_32_bit/register_32_bit.vcd
$date
	Fri Dec 11 10:41:58 2020
$end
$version
	Icarus Verilog
$end
$timescale
	1s
$end
$scope module tb_register_32_bit $end
$var wire 32 ! data_out [31:0] $end
$var reg 1 " clock $end
$var reg 32 # data_in [31:0] $end
$var reg 1 $ enable $end
$var reg 1 % reset $end
$scope module comp_1 $end
$var wire 1 " Clock $end
$var wire 32 & Data_In [31:0] $end
$var wire 1 $ Enable $end
$var wire 1 % Reset $end
$var reg 32 ' Data_Out [31:0] $end
$upscope $end
$upscope $end
$enddefinitions $end
#0
$dumpvars
bx '
b1010 &
1%
0$
b1010 #
0"
bx !
$end
#1
1"
#2
b0 !
b0 '
0"
b1011 #
b1011 &
0%
#3
1"
#4
0"
b1100 #
b1100 &
1%
#5
1"
#6
0"
b10101100 #
b10101100 &
#7
1"
#8
0"
b110010 #
b110010 &
#9
b110010 !
b110010 '
1"
1$
#10
0"
b1010000 #
b1010000 &
#11
b1010000 !
b1010000 '
1"
#12
0"
0$
#13
1"
#14
0"
b100000 #
b100000 &
#15
1"
#16
0"
b1011 #
b1011 &
#17
1"
#18
0"
b1100 #
b1100 &
#19
1"
#20
0"
b10101100 #
b10101100 &
#21
1"
#22
0"
b110010 #
b110010 &
#23
1"
#24
0"
b1010000 #
b1010000 &
#25
1"
#26
0"
b100000 #
b100000 &
