custom_gate_1/main.v
// iverilog -o main.vvp main.v

module custom_gate_1 (
    output wire F,
    input wire [2:0] ABC
);

    assign F = (ABC == 3'b001 ||
                ABC == 3'b011 ||
                ABC == 3'b100 ||
                ABC == 3'b110) ? 1'b1 : 1'b0;

endmodule

module tb_custom_gate_1 ();

reg [2:0] abc;
wire f;

custom_gate_1 gate_1(.F(f), .ABC(abc));

initial
    begin
        $dumpfile("custom_gate_1.vcd");
        $dumpvars(0, tb_custom_gate_1);
        abc = 3'b000;
        #1
        abc = 3'b001;
        #1
        abc = 3'b010;
        #1
        abc = 3'b011;
        #1
        abc = 3'b100;
        #1
        abc = 3'b101;
        #1
        abc = 3'b110;
        #1
        abc = 3'b111;
        $finish;
    end

always @(f)
    $monitor("time=%0t \t abc = %b y = %b", $time, abc, f);

endmodule

custom_gate_1/custom_gate_1.vcd
$date
	Wed Dec  2 11:50:28 2020
$end
$version
	Icarus Verilog
$end
$timescale
	1s
$end
$scope module tb_custom_gate_1 $end
$var wire 1 ! f $end
$var reg 3 " abc [2:0] $end
$scope module gate_1 $end
$var wire 3 # ABC [2:0] $end
$var wire 1 ! F $end
$upscope $end
$upscope $end
$enddefinitions $end
#0
$dumpvars
b0 #
b0 "
0!
$end
#1
1!
b1 "
b1 #
#2
0!
b10 "
b10 #
#3
1!
b11 "
b11 #
#4
b100 "
b100 #
#5
0!
b101 "
b101 #
#6
1!
b110 "
b110 #
#7
0!
b111 "
b111 #
