serial_bit_sequence/main.v
module serial_bit_sequence (
    output reg Data_Out,
    input wire Data_In, Clock, Reset
);

    // || Data_0 || Data_1 || Data_2 ||
    // ||    1   ||    1   ||    1   || --> will trigger Data_Out = 1

    // Declaration
    reg [4:0] Current_State, Next_State;
    parameter   Start           = 5'b00001,
                Data_0_Is_Set   = 5'b00010,
                Data_0_Not_Set  = 5'b00100,
                Data_1_Is_Set   = 5'b01000,
                Data_1_Not_Set  = 5'b10000;

    // State memory --> hanya untuk memindahkan dari Next_State to Current_State
    always @ (posedge Clock or negedge Reset)
        begin
            if (!Reset)
                Current_State <= Start;
            else
                Current_State <= Next_State;
        end

    // Next state --> memberikan aturan untuk mengatur aliran Next_State
    always @ (Current_State or Data_In)
        begin
            case (Current_State)
                Start           : if (Data_In == 1'b1) Next_State = Data_0_Is_Set;
                                  else Next_State = Data_0_Not_Set;
                Data_0_Is_Set   : if (Data_In == 1'b1) Next_State = Data_1_Is_Set;
                                  else Next_State = Data_1_Not_Set;
                Data_1_Is_Set   : Next_State = Start;
                Data_0_Not_Set  : Next_State = Data_1_Not_Set;
                Data_1_Not_Set  : Next_State = Start;
                default         : Next_State = Start;
            endcase
        end

    // Output --> mengatur output
    always @ (Current_State or Data_In)
        begin
            case (Current_State)
                Data_1_Is_Set   : if (Data_In == 1'b1) Data_Out = 1'b1;
                                  else Data_Out = 1'b0;
                default         : Data_Out = 1'b0;
            endcase
        end

endmodule

module tb_serial_bit_sequence();

    wire data_out;
    reg data_in, clock, reset;
    wire current_state, next_state;

    serial_bit_sequence DUT(.Data_Out(data_out), .Data_In(data_in), .Clock(clock), .Reset(reset));

    // Clock
    initial clock = 1'b0;
    always #1 clock = ~clock;

    // Reset
    initial reset = 1'b1;

    // Data in
    always
        begin
            $dumpfile("serial_bit_sequence.vcd");
            $dumpvars(0, tb_serial_bit_sequence);
            data_in = 1'b0;
            #1 data_in = 1'b1;
            #1 data_in = 1'b0;
            #2 data_in = 1'b1;
            #2 data_in = 1'b1;
            #2 data_in = 1'b1;
            #2 data_in = 1'b1;
            #2 data_in = 1'b1;
            #2 data_in = 1'b1;
            #2 data_in = 1'b1;
            #2 data_in = 1'b1;
            #2 data_in = 1'b1;
            $finish;
        end

endmodule

serial_bit_sequence/serial_bit_sequence.vcd
$date
	Tue Dec  8 16:18:41 2020
$end
$version
	Icarus Verilog
$end
$timescale
	1s
$end
$scope module tb_serial_bit_sequence $end
$var wire 1 ! data_out $end
$var reg 1 " clock $end
$var reg 1 # data_in $end
$var reg 1 $ reset $end
$scope module DUT $end
$var wire 1 " Clock $end
$var wire 1 # Data_In $end
$var wire 1 $ Reset $end
$var reg 5 % Current_State [4:0] $end
$var reg 1 ! Data_Out $end
$var reg 5 & Next_State [4:0] $end
$upscope $end
$upscope $end
$enddefinitions $end
#0
$dumpvars
b1 &
bx %
1$
0#
0"
0!
$end
#1
b10 &
b1 %
1#
1"
#2
b100 &
0#
0"
#3
b10000 &
b100 %
1"
#4
0"
1#
#5
b1 &
b10000 %
1"
#6
0"
#7
b10 &
b1 %
1"
#8
0"
#9
b1000 &
b10 %
1"
#10
0"
#11
b1 &
1!
b1000 %
1"
#12
0"
#13
0!
b10 &
b1 %
1"
#14
0"
#15
b1000 &
b10 %
1"
#16
0"
#17
1!
b1 &
b1000 %
1"
#18
0"
#19
b10 &
0!
b1 %
1"
