counter_clock_based/main.v
    module counter_block_based (
    output reg [15:0] Count_Out,
    input wire [15:0] Count_In,
    input wire Load, En, Clock, Reset            
);

    always @ (posedge Clock or negedge Reset)
        begin
            if (!Reset) Count_Out <= 16'b0;
            else
                if (En)
                    if (Load) Count_Out <= Count_In;
                    else Count_Out <= Count_Out + 1;    
        end

endmodule

module tb_counter_clock_based ();

    wire [15:0] count_out;
    reg [15:0] count_in;
    reg load, en, clock, reset;

    counter_block_based DUT(.Count_Out(count_out), .Count_In(count_in), .Load(load), .En(en), .Clock(clock), .Reset(reset));

    // Clock
    initial
        clock = 1'b0;
    always
        #1 clock = ~clock;

    // Enable
    initial
        begin
            en = 1'b0;
            #5 en = 1'b1;    
        end

    // Reset
    initial
        begin
            reset = 1'b1;
            #1 reset = 1'b0;
            #1 reset = 1'b1;
        end

    // Load
    initial
        load = 1'b0;

    initial
        begin
            $dumpfile("counter_clock_based.vcd");
            $dumpvars(0, tb_counter_clock_based);
            #10 load = 1'b1;
            count_in = 16'b0101110100101110;
            #2 load = 1'b0;
            #5;
            $finish;
        end

endmodule

counter_clock_based/counter_clock_based.vcd
$date
	Wed Dec  9 15:38:48 2020
$end
$version
	Icarus Verilog
$end
$timescale
	1s
$end
$scope module tb_counter_clock_based $end
$var wire 16 ! count_out [15:0] $end
$var reg 1 " clock $end
$var reg 16 # count_in [15:0] $end
$var reg 1 $ en $end
$var reg 1 % load $end
$var reg 1 & reset $end
$scope module DUT $end
$var wire 1 " Clock $end
$var wire 16 ' Count_In [15:0] $end
$var wire 1 $ En $end
$var wire 1 % Load $end
$var wire 1 & Reset $end
$var reg 16 ( Count_Out [15:0] $end
$upscope $end
$upscope $end
$enddefinitions $end
#0
$dumpvars
bx (
bx '
1&
0%
0$
bx #
0"
bx !
$end
#1
b0 !
b0 (
0&
1"
#2
1&
0"
#3
1"
#4
0"
#5
b1 !
b1 (
1"
1$
#6
0"
#7
b10 !
b10 (
1"
#8
0"
#9
b11 !
b11 (
1"
#10
0"
b101110100101110 #
b101110100101110 '
1%
#11
b101110100101110 !
b101110100101110 (
1"
#12
0"
0%
#13
b101110100101111 !
b101110100101111 (
1"
#14
0"
#15
b101110100110000 !
b101110100110000 (
1"
#16
0"
#17
b101110100110001 !
b101110100110001 (
1"
