structural_gate/main.v
`timescale 1ns/1ps

module structural_gate_0 (
    output wire F,
    input wire A, B, C
);

    wire An, Bn, Cn;
    wire net1, net2, net3, net4;

    not comp_1(An, A);
    not comp_2(Bn, B);
    not comp_3(Cn, C);

    and comp_4(net1, An, Bn, C);
    and comp_5(net2, An, B, C);
    and comp_6(net3, A, Bn, Cn);
    and comp_7(net4, A, B, C);

    or comp_8(F, net1, net2, net3, net4);

endmodule

module tb_structural_gate_0();
    wire f;
    reg a, b, c;

    structural_gate_0 comp_1(.F(f), .A(a), .B(b), .C(c));

    initial
        begin
            $dumpfile("structural_gate_0.vcd");
            $dumpvars(0, tb_structural_gate_0);
            a = 1'b0;
            b = 1'b0;
            c = 1'b0;
            #1
            a = 1'b0;
            b = 1'b0;
            c = 1'b1;
            #1
            a = 1'b0;
            b = 1'b1;
            c = 1'b0;
            #1
            a = 1'b0;
            b = 1'b1;
            c = 1'b1;
            #1
            a = 1'b1;
            b = 1'b0;
            c = 1'b0;
            #1
            a = 1'b1;
            b = 1'b0;
            c = 1'b1;
            #1
            a = 1'b1;
            b = 1'b1;
            c = 1'b0;
            #1
            a = 1'b1;
            b = 1'b1;
            c = 1'b1;
            #10
            $finish;            
        end

    always @(f)
        $monitor("time=%0t \t a = %b b = %b c = %b f = %b", $time, a, b, c, f);    

endmodule

structural_gate/structural_gate_0.vcd
$date
	Thu Dec  3 00:18:14 2020
$end
$version
	Icarus Verilog
$end
$timescale
	1ps
$end
$scope module tb_structural_gate_0 $end
$var wire 1 ! f $end
$var reg 1 " a $end
$var reg 1 # b $end
$var reg 1 $ c $end
$scope module comp_1 $end
$var wire 1 " A $end
$var wire 1 % An $end
$var wire 1 # B $end
$var wire 1 & Bn $end
$var wire 1 $ C $end
$var wire 1 ' Cn $end
$var wire 1 ! F $end
$var wire 1 ( net1 $end
$var wire 1 ) net2 $end
$var wire 1 * net3 $end
$var wire 1 + net4 $end
$upscope $end
$upscope $end
$enddefinitions $end
#0
$dumpvars
0+
0*
0)
0(
1'
1&
1%
0$
0#
0"
0!
$end
#1000
1!
0'
1(
1$
#2000
0!
1'
0(
0&
0$
1#
#3000
1!
0'
1)
1$
#4000
1*
1!
1'
1&
0)
0%
0$
0#
1"
#5000
0!
0*
0'
1$
#6000
1'
0&
0$
1#
#7000
1!
0'
1+
1$
