dataflow_gate_2/main.v
/*
Implementation of custom gate POS: 0,1,3,5,7
Created by jefflgaol@icloud.com
*/

module dataflow_gate_2 (
    output wire F,
    input wire A, B, C
);

    assign F = (A  | B  | C)  &
               (A  | B  | ~C) &
               (A  | ~B | ~C) &
               (~A | B  | ~C) &
               (~A | ~B | ~C);

endmodule

module tb_dataflow_gate_2 ();

reg a, b, c;
wire f;

dataflow_gate_2 gate_1(.F(f), .A(a), .B(b), .C(c));

initial
    begin
        $dumpfile("dataflow_gate_2.vcd");
        $dumpvars(0, tb_dataflow_gate_2);
        a = 1'b0;
        b = 1'b0;
        c = 1'b0;
        #1
        a = 1'b0;
        b = 1'b0;
        c = 1'b1;
        #1
        a = 1'b0;
        b = 1'b1;
        c = 1'b0;
        #1
        a = 1'b0;
        b = 1'b1;
        c = 1'b1;
        #1
        a = 1'b1;
        b = 1'b0;
        c = 1'b0;
        #1
        a = 1'b1;
        b = 1'b0;
        c = 1'b1;
        #1
        a = 1'b1;
        b = 1'b1;
        c = 1'b0;
        #1
        a = 1'b1;
        b = 1'b1;
        c = 1'b1;
        $finish;
    end

always @(f)
    $monitor("time=%0t \t a = %b b = %b c = %b y = %b", $time, a, b, c, f);

endmodule

dataflow_gate_2/dataflow_gate_2.vcd
$date
	Thu Dec  3 00:21:57 2020
$end
$version
	Icarus Verilog
$end
$timescale
	1s
$end
$scope module tb_dataflow_gate_2 $end
$var wire 1 ! f $end
$var reg 1 " a $end
$var reg 1 # b $end
$var reg 1 $ c $end
$scope module gate_1 $end
$var wire 1 " A $end
$var wire 1 # B $end
$var wire 1 $ C $end
$var wire 1 ! F $end
$upscope $end
$upscope $end
$enddefinitions $end
#0
$dumpvars
0$
0#
0"
0!
$end
#1
1$
#2
1!
0$
1#
#3
0!
1$
#4
1!
0$
0#
1"
#5
0!
1$
#6
1!
0$
1#
#7
0!
1$
