inertial_delay_gate/main.v

/*
Implementation of inertial delay gate
Created by jefflgaol@icloud.com
*/

module inertial_delay_gate (
    output wire F,
    input wire [3:0] ABCD
);

    assign #(1:2:3) F = (ABCD == 4'b0011) ? 1'b0 :
                        (ABCD == 4'b0111) ? 1'b0 :
                        (ABCD == 4'b1011) ? 1'b0 :
                        (ABCD == 4'b1111) ? 1'b0 :
                        1'b1;

endmodule

module tb_inertial_delay_gate ();

wire f;
reg [3:0] abcd;

inertial_delay_gate gate_1(f, abcd);

initial
    begin
        $dumpfile("inertial_delay_gate.vcd");
        $dumpvars(0, tb_inertial_delay_gate);
        abcd = 4'b0000;
        #1
        abcd = 4'b0001;
        #1
        abcd = 4'b0010;
        #1
        abcd = 4'b0011;
        #1
        abcd = 4'b0100;
        #1
        abcd = 4'b0101;
        #1
        abcd = 4'b0110;
        #1
        abcd = 4'b0111;
        #1
        abcd = 4'b1000;
        #1
        abcd = 4'b1001;
        #1
        abcd = 4'b1010;
        #1
        abcd = 4'b1011;
        #1
        abcd = 4'b1100;
        #1
        abcd = 4'b1101;
        #1
        abcd = 4'b1110;
        #1
        abcd = 4'b1111;
        $finish;
    end

always @(f)
    $monitor("time=%0t \t abcd = %b f = %b", $time, abcd, f);

endmodule

inertial_delay_gate/inertial_delay_gate.vcd
$date
	Wed Dec  2 15:09:52 2020
$end
$version
	Icarus Verilog
$end
$timescale
	1s
$end
$scope module tb_inertial_delay_gate $end
$var wire 1 ! f $end
$var reg 4 " abcd [3:0] $end
$scope module gate_1 $end
$var wire 4 # ABCD [3:0] $end
$var wire 1 ! F $end
$upscope $end
$upscope $end
$enddefinitions $end
#0
$dumpvars
b0 #
b0 "
x!
$end
#1
b1 "
b1 #
#2
b10 "
b10 #
1!
#3
b11 "
b11 #
#4
b100 "
b100 #
#5
b101 "
b101 #
#6
b110 "
b110 #
#7
b111 "
b111 #
#8
b1000 "
b1000 #
#9
b1001 "
b1001 #
#10
b1010 "
b1010 #
#11
b1011 "
b1011 #
#12
b1100 "
b1100 #
#13
b1101 "
b1101 #
#14
b1110 "
b1110 #
#15
b1111 "
b1111 #
